{"title":"Acetylcholinesterase Inhibition leading to Acute Mortality via Impaired Coordination & Movement​","keyEvents":[{"id":12,"type":"molecular-initiating-event"},{"id":360,"type":"adverse-outcome"},{"id":1705,"type":"key-event"},{"id":39,"type":"key-event"},{"id":351,"type":"adverse-outcome"},{"id":10,"type":"key-event"}],"id":312}
{"title":"Inhibition of complex I of the electron transport chain leading to chemical induced Fanconi syndrome","keyEvents":[{"id":888,"type":"molecular-initiating-event"},{"id":1564,"type":"adverse-outcome"},{"id":1477,"type":"key-event"},{"id":887,"type":"key-event"},{"id":1562,"type":"key-event"},{"id":1563,"type":"key-event"}],"id":276}
